iofree/__init__.py
iofree/exceptions.py
iofree/schema.py
iofree/contrib/common.py
iofree/contrib/socks5.py
iofree-0.2.5.dist-info/licenses/LICENSE
iofree-0.2.5.dist-info/WHEEL
iofree-0.2.5.dist-info/METADATA
iofree-0.2.5.dist-info/RECORD
