Metadata-Version: 2.4
Name: iofree
Version: 0.2.5
Summary: `iofree` is an easy-to-use and powerful library to help you implement network protocols and binary parsers.
Keywords: binary-parser,Sans-IO,io-free
Author-email: Yingbo Gu <tensiongyb@gmail.com>
Maintainer-email: Yingbo Gu <tensiongyb@gmail.com>
Requires-Python: >=3.6
Classifier: License :: OSI Approved :: MIT License
Classifier: Intended Audience :: Developers
Classifier: Programming Language :: Python :: 3.6
Classifier: Programming Language :: Python :: 3.7
Classifier: Programming Language :: Python :: 3.8
Classifier: Programming Language :: Python :: 3.9
Classifier: Programming Language :: Python :: 3.10
Classifier: Programming Language :: Python :: 3.11
Classifier: Programming Language :: Python :: 3.12
Classifier: Programming Language :: Python :: 3.13
Classifier: Programming Language :: Python :: 3.14
License-File: LICENSE
Project-URL: Source, https://github.com/guyingbo/iofree
